{
  "links": {
    "link1": {
      "linkName": "Bob's Law Blog",
      "link": "www.google.com",
      "status": true,
      "type": "Blogs",
      "uid": "Rfishernc"
    },
    "link2": {
      "linkName": "React For Dummies",
      "link": "www.google.com",
      "status": false,
      "type": "Tutorials",
      "uid": "Rfishernc"
    },
    "link3": {
      "linkName": "Bob's Law Blog",
      "link": "www.google.com",
      "status": true,
      "type": "Blogs",
      "uid": "Rfishernc"
    },
    "link4": {
      "linkName": "React For Dummies",
      "link": "www.google.com",
      "status": false,
      "type": "Tutorials",
      "uid": "Rfishernc"
    },
    "link5": {
      "linkName": "Bob's Law Blog",
      "link": "www.google.com",
      "status": true,
      "type": "Blogs",
      "uid": "Rfishernc"
    },
    "link6": {
      "linkName": "React For Dummies",
      "link": "www.google.com",
      "status": false,
      "type": "Tutorials",
      "uid": "Rfishernc"
    },
    "link7": {
      "linkName": "Bob's Law Blog",
      "link": "www.google.com",
      "status": true,
      "type": "Blogs",
      "uid": "Rfishernc"
    },
    "link8": {
      "linkName": "React For Dummies",
      "link": "www.google.com",
      "status": false,
      "type": "Tutorials",
      "uid": "Rfishernc"
    }
  }
}